pyhatchbabyrest/__init__.py
pyhatchbabyrest/constants.py
pyhatchbabyrest/pyhatchbabyrest.py
pyhatchbabyrest/pyhatchbabyrestasync.py
pyhatchbabyrest_hass-2.3.0.dist-info/LICENSE
pyhatchbabyrest_hass-2.3.0.dist-info/METADATA
pyhatchbabyrest_hass-2.3.0.dist-info/WHEEL
pyhatchbabyrest_hass-2.3.0.dist-info/top_level.txt
pyhatchbabyrest_hass-2.3.0.dist-info/RECORD
